MANIFEST.in
PYPI_VERSION
README.md
requirements.txt
setup.cfg
setup.py
bin/convert_to_png.sh
bin/get-owm-data.py
pi3dpf_ns/__init__.py
pi3dpf_ns/__pycache__/__init__.cpython-37.pyc
pi3dpf_ns/pi3dpf_owm/__init__.py
pi3dpf_ns/pi3dpf_owm/common.x/__init__.py
pi3dpf_ns/pi3dpf_owm/common.x/pf.functions.sh
pi3dpf_ns/pi3dpf_owm/common.x/pf_common.py
pi3dpf_ns/pi3dpf_owm/owm_org/__init__.py
pi3dpf_ns/pi3dpf_owm/owm_org/openweathermap.py
pi3dpf_ns/pi3dpf_owm/owm_org/openweathermapToerikflowers_wi.py
pi3dpf_ns/pi3dpf_owm/owm_org/pythainlp_util_date.py
pi3dpf_ns/pi3dpf_owm/owm_org/suncalc.py
pi3dpf_ns/pi3dpf_owm/owm_org/cfg/wm.config
pi3dpf_ns/pi3dpf_owm/owm_org/cfg/fonts/NotoSans.and.Thai.and.Weather.ttf
pi3dpf_ns/pi3dpf_owm/owm_org/cfg/fonts/erikflowers.github.io_weather-font-icons.xlsx
pi3dpf_ns/pi3dpf_owm/owm_org/cfg/fonts/weathericons-regular-webfont.ttf
pi3dpf_ns/pi3dpf_owm/owm_org/cfg/templates/owm-weather-5d3h.ods
pi3dpf_ns/pi3dpf_owm/owm_org/cfg/templates/owm-weather-5d3h.ods-sav
pi3dpf_ns/pi3dpf_owm/owm_org/cfg/templates/owm-weather-5d3h.ods-sav2
pi3dpf_ns/pi3dpf_owm/owm_org/cfg/templates/owm-weather-now-2-cities.odp
pi3dpf_ns_pi3dpf_owm.egg-info/PKG-INFO
pi3dpf_ns_pi3dpf_owm.egg-info/SOURCES.txt
pi3dpf_ns_pi3dpf_owm.egg-info/dependency_links.txt
pi3dpf_ns_pi3dpf_owm.egg-info/not-zip-safe
pi3dpf_ns_pi3dpf_owm.egg-info/requires.txt
pi3dpf_ns_pi3dpf_owm.egg-info/top_level.txt