Metadata-Version: 2.1
Name: pi3dpf-ns-pi3dpf-owm
Version: 0.1.356
Summary: Module to compile OpenWeatherMap based weather forecasts for display in pi3d based picture frame
Home-page: https://github.com/satnerd/pi3dpf-pictureframe
Author: Beat Hess
Author-email: ht8@gmx.net
Maintainer: Beat Hess
Maintainer-email: ht8@gmx.net
License: GPLv3
Project-URL: Documentation, https://github.com/satnerd/pi3dpf-pictureframe
Keywords: pi3d,owm weather,alexa
Platform: UNKNOWN
Classifier: Development Status :: 4 - Beta
Classifier: Intended Audience :: End Users/Desktop
Classifier: Topic :: Multimedia :: Graphics :: Presentation
Classifier: License :: OSI Approved :: GNU General Public License v3 (GPLv3)
Classifier: Programming Language :: Python
Classifier: Programming Language :: Python :: 3.7
Requires-Python: >=3.7
